sidebar/__init__.py
sidebar/apps.py
sidebar/urls.py
sidebar/views.py
sidebar/migrations/__init__.py
sidebar/static/sidebar/sidebar.css
sidebar/static/sidebar/sidebar.js
sidebar/templates/sidebar/main.html
micro_sidebar-1.2.2.dist-info/LICENSE
micro_sidebar-1.2.2.dist-info/METADATA
micro_sidebar-1.2.2.dist-info/WHEEL
micro_sidebar-1.2.2.dist-info/top_level.txt
micro_sidebar-1.2.2.dist-info/RECORD
