Metadata-Version: 2.1
Name: micro-sidebar
Version: 1.2.2
Summary: A Reusable RTL Django Sidebar App
Home-page: https://github.com/debeski/micro-sidebar
Author: DeBeski
Author-email: DeBeski <debeski1@gmail.com>
License: MIT
Project-URL: Homepage, https://github.com/debeski/micro-sidebar
Classifier: Framework :: Django
Classifier: Framework :: Django :: 5
Classifier: Programming Language :: Python :: 3
Classifier: Programming Language :: Python :: 3.8
Classifier: Programming Language :: Python :: 3.9
Classifier: Programming Language :: Python :: 3.10
Classifier: Programming Language :: Python :: 3.11
Classifier: Programming Language :: Python :: 3.12
Classifier: Programming Language :: Python :: 3.13
Classifier: Programming Language :: Python :: 3.14
Classifier: License :: OSI Approved :: MIT License
Classifier: Operating System :: OS Independent
Requires-Python: >=3.9
License-File: LICENSE
Requires-Dist: Django (>=5.1)
